Metadata-Version: 2.1
Name: tapi-wrapper2
Version: 0.1.3
Summary: Python API client generator
Home-page: https://github.com/pavelmaksimov/tapi-wrapper
Author: Filipe Ximenes
Author-email: filipeximenes@gmail.com
License: MIT
Keywords: tapi,wrapper,api
Platform: UNKNOWN
Requires-Python: >=3.5
